jupyter_conda/__init__.py
jupyter_conda/_version.py
jupyter_conda/envmanager.py
jupyter_conda/handlers.py
jupyter_conda/log.py
jupyter_conda/rest_api.yml
jupyter_conda/server.py
jupyter_conda/static/common.js
jupyter_conda/static/conda.css
jupyter_conda/static/main.js
jupyter_conda/static/menu.html
jupyter_conda/static/models.js
jupyter_conda/static/tab.html
jupyter_conda/static/tree.js
jupyter_conda/static/urls.js
jupyter_conda/static/views.js
jupyter_conda/tests/__init__.py
jupyter_conda/tests/test_actionsstack.py
jupyter_conda/tests/test_api.py
jupyter_conda/tests/test_notebook.py
jupyter_conda/tests/utils.py
jupyter_conda/tests/js/_utils.js
jupyter_conda/tests/js/test_notebook_basic.js
jupyter_conda-3.4.1.data/data/etc/jupyter/jupyter_notebook_config.d/jupyter_conda.json
jupyter_conda-3.4.1.data/data/etc/jupyter/nbconfig/notebook.d/jupyter_conda.json
jupyter_conda-3.4.1.data/data/etc/jupyter/nbconfig/tree.d/jupyter_conda.json
jupyter_conda-3.4.1.data/data/share/jupyter/nbextensions/jupyter_conda/common.js
jupyter_conda-3.4.1.data/data/share/jupyter/nbextensions/jupyter_conda/conda.css
jupyter_conda-3.4.1.data/data/share/jupyter/nbextensions/jupyter_conda/main.js
jupyter_conda-3.4.1.data/data/share/jupyter/nbextensions/jupyter_conda/menu.html
jupyter_conda-3.4.1.data/data/share/jupyter/nbextensions/jupyter_conda/models.js
jupyter_conda-3.4.1.data/data/share/jupyter/nbextensions/jupyter_conda/tab.html
jupyter_conda-3.4.1.data/data/share/jupyter/nbextensions/jupyter_conda/tree.js
jupyter_conda-3.4.1.data/data/share/jupyter/nbextensions/jupyter_conda/urls.js
jupyter_conda-3.4.1.data/data/share/jupyter/nbextensions/jupyter_conda/views.js
jupyter_conda-3.4.1.dist-info/LICENSE
jupyter_conda-3.4.1.dist-info/METADATA
jupyter_conda-3.4.1.dist-info/WHEEL
jupyter_conda-3.4.1.dist-info/top_level.txt
jupyter_conda-3.4.1.dist-info/RECORD
