Metadata-Version: 2.1
Name: jupyter-conda
Version: 3.4.1
Summary: Manage your conda environments from the Jupyter Notebook and JupyterLab
Home-page: https://github.com/fcollonval/jupyter_conda
Author: Continuum Analytics, Frederic Collonval
License: UNKNOWN
Platform: UNKNOWN
Requires-Dist: nb-conda-kernels (>=2.2.0)
Requires-Dist: notebook (>=4.3.1)
Requires-Dist: packaging
Requires-Dist: typing ; python_version < "3.7"
Provides-Extra: test
Requires-Dist: coverage ; extra == 'test'
Requires-Dist: flake8 ; extra == 'test'
Requires-Dist: pytest ; extra == 'test'
Requires-Dist: pytest-asyncio ; extra == 'test'
Requires-Dist: requests ; extra == 'test'
